xlstools/__init__.py
xlstools/csv_reader.py
xlstools/google_sheet_reader.py
xlstools/open_xl.py
xlstools/openpyxlrd.py
xlstools/pd_emulator.py
xlstools/util.py
xlstools/xl_reader.py
xlstools/xl_sheet.py
xlstools/xlrd_like.py
xlstools-0.1.6.dist-info/LICENSE
xlstools-0.1.6.dist-info/METADATA
xlstools-0.1.6.dist-info/WHEEL
xlstools-0.1.6.dist-info/top_level.txt
xlstools-0.1.6.dist-info/RECORD
