Metadata-Version: 2.1
Name: xlstools
Version: 0.1.6
Home-page: https://github.com/scope3/xls-tools
Author: Brandon Kuczenski
Author-email: brandon@scope3consulting.com
License-File: LICENSE
Requires-Dist: xlrd >=2.0.0
Requires-Dist: openpyxl >=3.0.7
Provides-Extra: gsheet
Requires-Dist: google-api-python-client >=2.2.0 ; extra == 'gsheet'
Requires-Dist: oauth2client >=4.1.3 ; extra == 'gsheet'
